setup.py
bin/html2dt
html2dt/__init__.py
html2dt.egg-info/PKG-INFO
html2dt.egg-info/SOURCES.txt
html2dt.egg-info/dependency_links.txt
html2dt.egg-info/not-zip-safe
html2dt.egg-info/top_level.txt