Metadata-Version: 1.0
Name: html2dt
Version: 1.1
Summary: Convert html file to django template file.
Home-page: https://github.com/prakash09/html2django_template
Author: Prakash Kumar
Author-email: prakash.gbpec@gmail.com
License: MIT
Platform: UNKNOWN
